dig_ass_ocr_protos/DigitalAssistantOCR_pb2.py
dig_ass_ocr_protos/DigitalAssistantOCR_pb2.pyi
dig_ass_ocr_protos/DigitalAssistantOCR_pb2_grpc.py
dig_ass_ocr_protos/__init__.py
dig_ass_ocr_protos/client.py
dig_ass_ocr_protos-2.0.2.dist-info/METADATA
dig_ass_ocr_protos-2.0.2.dist-info/WHEEL
dig_ass_ocr_protos-2.0.2.dist-info/top_level.txt
dig_ass_ocr_protos-2.0.2.dist-info/RECORD
