Metadata-Version: 2.4
Name: dig_ass_ocr_protos
Version: 2.0.2
Summary: Proto files for dig_ass_ocr_protos
Author: AGI-MED-TEAM
Requires-Python: >=3.13
Requires-Dist: agi-med-protos==2.2.0
